LICENSE
MANIFEST.in
README.md
setup.py
docs/Makefile
docs/source/conf.py
docs/source/index.rst
docs/source/installation.rst
docs/source/reference.rst
docs/source/usage.rst
ntokloapi/__init__.py
ntokloapi/blacklist.py
ntokloapi/charts.py
ntokloapi/config.py
ntokloapi/events.py
ntokloapi/exceptions.py
ntokloapi/ntokloapi.py
ntokloapi/products.py
ntokloapi/recommendations.py
ntokloapi/utils.py
ntokloapi.egg-info/PKG-INFO
ntokloapi.egg-info/SOURCES.txt
ntokloapi.egg-info/dependency_links.txt
ntokloapi.egg-info/not-zip-safe
ntokloapi.egg-info/requires.txt
ntokloapi.egg-info/top_level.txt
tests/config.py
tests/test_blacklist.py