Metadata-Version: 1.1
Name: ntokloapi
Version: 0.1
Summary: Manage your nToklo recommendations through the API
Home-page: https://github.com/nToklo/ntokloapi-python
Author: Oscar Carballal Prego
Author-email: oscar.carballal@ntoklo.com
License: Apache 2.0 license, see LICENSE
Platform: UNKNOWN
Classifier: Development Status :: 5 - Production/Stable
Classifier: Environment :: Web Environment
Classifier: Intended Audience :: Developers
Classifier: Operating System :: POSIX :: Linux
Classifier: Operating System :: Unix
Classifier: License :: OSI Approved :: Apache Software License
Classifier: Programming Language :: Python :: 2.7
Classifier: Programming Language :: Python :: 3.3
Classifier: Programming Language :: Python :: 3.4
